{"status":1,"error":{},"context":{"results":[{"name":"Distance","param":"distance","ui_type":2,"options":[{"min":0,"max":50}]},{"id":1,"name":"Price Range","param":"price_range","ui_type":3,"options":[{"min":0,"max":15000.0}]},{"id":3,"name":"Space Setup","param":"space_setup","ui_type":1,"options":[{"id":1,"name":"Classroom","icon":"/media/letsmeet/space_setup/classroom_o2XohcP.png","icon_name":"Classroom"},{"id":2,"name":"Banquet","icon":"/media/letsmeet/space_setup/banquet.png","icon_name":"Banquet"},{"id":3,"name":"Theatre","icon":"/media/letsmeet/space_setup/theatre.png","icon_name":"Theatre"},{"id":4,"name":"U Shaped","icon":"/media/letsmeet/space_setup/ushaped.png","icon_name":"U Shaped"},{"id":5,"name":"Boardroom","icon":"/media/letsmeet/space_setup/boardroom.png","icon_name":"Board Room"},{"id":6,"name":"Office","icon":"/media/letsmeet/space_setup/office.png","icon_name":"office_setup"}]},{"id":4,"name":"Capacity","param":"capacity","ui_type":2,"options":[{"min":0,"max":123}]},{"id":3,"name":"Amenities","param":"amenities","ui_type":1,"options":[{"id":29,"name":"Coffee","app_icon":"coffee","icon":"/media/amenities/test-2.png"},{"id":21,"name":"Flipchart","app_icon":"flipchart","icon":"/media/amenities/test-7.png"},{"id":22,"name":"HDMI","app_icon":"hdmi","icon":"/media/amenities/test-10.png"},{"id":5,"name":"Printer","app_icon":"printer","icon":"/media/facilities/f_printer.png"},{"id":23,"name":"Projector","app_icon":"projector","icon":"/media/amenities/test-8.png"},{"id":30,"name":"Sanitizer","app_icon":"sanitizer","icon":"/media/amenities/test.png"},{"id":24,"name":"Stationary","app_icon":"stationary","icon":"/media/amenities/test-9.png"},{"id":28,"name":"Tea","app_icon":"tea","icon":"/media/amenities/test-3.png"},{"id":25,"name":"TV","app_icon":"tv","icon":"/media/amenities/test-4.png"},{"id":27,"name":"Water","app_icon":"water","icon":"/media/amenities/test-5.png"},{"id":26,"name":"Whiteboard","app_icon":"whiteboard","icon":"/media/amenities/test-1.png"}]}]}}